.gitattributes
.gitignore
.travis.yml
LICENSE
MANIFEST.in
README.md
RELEASING.md
pyproject.toml
requirements-dev.txt
requirements.txt
setup.cfg
setup.py
versioneer.py
depository/__init__.py
depository/_version.py
depository.egg-info/PKG-INFO
depository.egg-info/SOURCES.txt
depository.egg-info/dependency_links.txt
depository.egg-info/requires.txt
depository.egg-info/top_level.txt