Metadata-Version: 2.1
Name: depository
Version: 0.1
Summary: Storage Workflows for Notebooks
Home-page: https://github.com/nteract/depository
Author: nteract contributors
Author-email: nteract@googlegroups.com
License: BSD
Project-URL: Documentation, https://github.com/nteract/depository/#todo
Project-URL: Funding, https://nteract.io
Project-URL: Source, https://github.com/nteract/depository/
Project-URL: Tracker, https://github.com/nteract/depository/issues
Keywords: jupyter storage nteract notebook
Platform: UNKNOWN
Classifier: Intended Audience :: Developers
Classifier: Intended Audience :: System Administrators
Classifier: Intended Audience :: Science/Research
Classifier: License :: OSI Approved :: BSD License
Classifier: Programming Language :: Python
Classifier: Programming Language :: Python :: 3
Classifier: Programming Language :: Python :: 2.7
Provides-Extra: test
Provides-Extra: dev
